streamlit_awesome_search/__init__.py
streamlit_awesome_search/awesome_pandas.py
streamlit_awesome_search-0.1.1.dist-info/LICENSE
streamlit_awesome_search-0.1.1.dist-info/METADATA
streamlit_awesome_search-0.1.1.dist-info/WHEEL
streamlit_awesome_search-0.1.1.dist-info/top_level.txt
streamlit_awesome_search-0.1.1.dist-info/RECORD
