Metadata-Version: 2.1
Name: streamlit-awesome-search
Version: 0.1.1
Summary: A streamlit search helper tool package
Author-email: dustin D <ediajin@126.com>
Classifier: Programming Language :: Python :: 3
Classifier: License :: OSI Approved :: MIT License
Classifier: Operating System :: OS Independent
Requires-Python: >=3.10
License-File: LICENSE
